crewplus-0.2.94.dist-info/METADATA
crewplus-0.2.94.dist-info/WHEEL
crewplus-0.2.94.dist-info/entry_points.txt
crewplus-0.2.94.dist-info/licenses/LICENSE
crewplus/__init__.py
crewplus/callbacks/__init__.py
crewplus/callbacks/async_langfuse_handler.py
crewplus/services/__init__.py
crewplus/services/azure_chat_model.py
crewplus/services/claude_chat_model.py
crewplus/services/feedback.md
crewplus/services/feedback_manager.py
crewplus/services/gemini_chat_model.py
crewplus/services/init_services.py
crewplus/services/model_load_balancer.py
crewplus/services/schemas/feedback.py
crewplus/services/tracing_manager.py
crewplus/utils/__init__.py
crewplus/utils/schema_action.py
crewplus/utils/schema_document_updater.py
crewplus/utils/tracing_util.py
crewplus/vectorstores/milvus/__init__.py
crewplus/vectorstores/milvus/milvus_schema_manager.py
crewplus/vectorstores/milvus/schema_milvus.py
crewplus/vectorstores/milvus/vdb_service.py
docs/GeminiChatModel.md
docs/ModelLoadBalancer.md
docs/VDBService.md
docs/index.md
crewplus-0.2.94.dist-info/RECORD
