Metadata-Version: 2.1
Name: crewplus
Version: 0.2.94
Summary: Base services for CrewPlus AI applications
Author-Email: Tim Liu <tim@opsmateai.com>
License: MIT
Project-URL: Homepage, https://github.com/your-org/crewplus-base
Project-URL: Documentation, https://crewplus.readthedocs.io
Project-URL: Repository, https://github.com/your-org/crewplus-base
Project-URL: Issues, https://github.com/your-org/crewplus-base/issues
Requires-Python: <4.0,>=3.11
Requires-Dist: langchain<1.0.0,>=0.3.25
Requires-Dist: langchain-openai>=0.3.24
Requires-Dist: google-genai>=1.21.1
Requires-Dist: anthropic[vertex]>=0.76.0
Requires-Dist: langchain-milvus<0.3.0,>=0.2.1
Requires-Dist: langfuse<4.0.0,>=3.1.3
